Metadata-Version: 2.1
Name: pro-video-ferramentas-suelen-24
Version: 1.0
Summary: Este pacote irá fornecer ferramentas de processamento de vídeo
Author: Suelen
Author-email: suelen@email.com
Keywords: camera,video,processamento
License-File: license.txt
